{
  "productDetails": {
    "productName": "Unsecured Personal Loans",
    "productCode": "LNUPL",
    "productStages": [

      {
        "id": "orientation",
        "previousStage": null,
        "nextStagename": "requirements",
        "name": "orientation",
        "sequenceNumber": 1,
        "isComplete": false,
        "location": "",
        "stages": null
      },
      {
        "id": "requirements",
        "previousStage": "orientation",
        "nextStagename": "application-form",
        "name": "loanRequirements",
        "sequenceNumber": 2,
        "isComplete": false,
        "location": "",
        "stages": null
      },
            {
        "id": "application-form",
        "previousStage": "requirements",
        "nextStagename": "offers-insurance",
        "name": "application",
        "sequenceNumber": 3,
        "isComplete": false,
        "stages": [
          {
            "id": "personal-details",
            "previousStage": null,
            "nextStagename": "financial-template-base",
            "name": "personalDetails",
            "sequenceNumber": 1,
            "isComplete": false,
            "stages": [
              {
                "id": "primary-registration",
                "previousStage": "expense-info",
                "nextStagename": "identity-info",
                "name": "primaryInformation",
                "sequenceNumber": 1,
                "isComplete": false,
                "stages": null
              },
              {
                "id": "identity-info",
                "previousStage": "primary-registration",
                "nextStagename": "contact-info",
                "name": "proofOfIdentity",
                "sequenceNumber": 2,
                "isComplete": false,
                "stages": null
              },
              {
                "id": "contact-info",
                "previousStage": "identity-info",
                "nextStagename": "occupation-info",
                "name": "contactInformation",
                "sequenceNumber": 3,
                "isComplete": false,
                "stages": null
              },
              {
                "id": "occupation-info",
                "previousStage": "contact-info",
                "nextStagename": null,
                "name": "employmentInformation",
                "sequenceNumber": 4,
                "isComplete": false,
                "stages": null
              }
            ]
          },
          {
            "id": "financial-template-base",
            "previousStage": "personal-details",
            "nextStagename": null,
            "name": "financialDetails",
            "sequenceNumber": 2,
            "isComplete": false,
            "stages": [
              {
                "id": "financial-details",
                "previousStage": null,
                "nextStagename":null,
                "name": "financialDetails",
                "sequenceNumber": 2,
                "isComplete": false,
                "stages": [
                  {
                    "id": "income-info",
                    "previousStage": null,
                    "nextStagename": "expense-info",
                    "name": "income",
                    "sequenceNumber": 1,
                    "isComplete": false,
                    "stages": null,
                    "type": "INCOME"
                  },
                  {
                    "id": "expense-info",
                    "previousStage": "income-info",
                    "nextStagename": "assets-info",
                    "name": "expenses",
                    "sequenceNumber": 2,
                    "isComplete": false,
                    "stages": null,
                    "type": "EXPENSE"
                  },
                  {
                    "id": "assets-info",
                    "previousStage": "expense-info",
                    "nextStagename": "liabilities-info",
                    "name": "assets",
                    "sequenceNumber": 3,
                    "isComplete": false,
                    "stages": null,
                    "type": "ASSET"
                  },
                  {
                    "id": "liabilities-info",
                    "previousStage": "assets-info",
                    "nextStagename": "current-assets-info",
                    "name": "liabilities",
                    "sequenceNumber": 4,
                    "isComplete": false,
                    "stages": null,
                    "type": "LIABILITY"
                  },
                  {
                    "id": "current-assets-info",
                    "previousStage": "liabilities-info",
                    "nextStagename": "current-liabilities-info",
                    "name": "currentAssets",
                    "sequenceNumber": 5,
                    "isComplete": false,
                    "stages": null,
                    "type": "CURRENT-ASSET"
                  },
                  {
                    "id": "current-liabilities-info",
                    "previousStage": "current-assets-info",
                    "nextStagename": null,
                    "name": "currentLiabilities",
                    "sequenceNumber": 6,
                    "isComplete": false,
                    "stages": null,
                    "type": "CURRENT-LIABILITY"
                  }
                ]
              }
            ]
          }
        ]
      },
      {
        "id": "offers-insurance",
        "previousStage": "application-form",
        "nextStagename": "review",
        "name": "offerDetails",
        "sequenceNumber": 4,
        "isComplete": false,
        "stages": [
          {
            "id": "offers",
            "previousStage": null,
            "nextStagename": null,
            "name": "offers",
            "sequenceNumber": 1,
            "isComplete": false,
            "stages": null
          }
        ]
      },
      {
        "id": "review",
        "previousStage": "offers-insurance",
        "nextStagename": "submission-confirmation",
        "name": "review",
        "sequenceNumber": 5,
        "isComplete": false,
        "stages": null
      },
      {
        "id": "submission-confirmation",
        "previousStage": null,
        "nextStagename": null,
        "name": "submissionConfirmation",
        "sequenceNumber":6,
        "isComplete": false,
        "stages": null
      }
    ]
  }
}
