{
	"list": [{
		"party": {
			"displayValue": "***624",
			"value": "D0F62A5CEC53EB985DBA69D5373F9BECFA40137819A3"
		},
		"requestType": "OTHERS",
		"requestData": "&#x7b;&quot;elements&quot;&#x3a;&#x5b;&#x7b;&quot;id&quot;&#x3a;&quot;SCH1&quot;,&quot;type&quot;&#x3a;&quot;SCH&quot;,&quot;label&quot;&#x3a;null,&quot;values&quot;&#x3a;&#x5b;&#x5d;,&quot;displayValues&quot;&#x3a;&#x5b;&#x5d;&#x7d;,&#x7b;&quot;id&quot;&#x3a;&quot;SBH2&quot;,&quot;type&quot;&#x3a;&quot;SBH&quot;,&quot;label&quot;&#x3a;null,&quot;values&quot;&#x3a;&#x5b;&#x5d;,&quot;displayValues&quot;&#x3a;&#x5b;&#x5d;&#x7d;,&#x7b;&quot;id&quot;&#x3a;&quot;FFTB3&quot;,&quot;type&quot;&#x3a;&quot;FFTB&quot;,&quot;label&quot;&#x3a;&quot;L1&quot;,&quot;values&quot;&#x3a;&#x5b;&#x5d;,&quot;displayValues&quot;&#x3a;&#x5b;&quot;&#x5e;&quot;&#x5d;&#x7d;&#x5d;&#x7d;",
		"entityTypeIdentifier": "66667777888894339",
		"status": "PE",
		"priority": "M",
		"creationDate": "2018-04-30T10:10:34.000Z",
		"id": "422",
		"entityTypeIdentifierKey": "DE",
		"lastUpdatedDate": "2018-04-30T10:10:34.659Z",
		"definitionId": "SR0000000420",
		"product": "TD",
		"categoryType": "Term Deposit",
		"priorityType": "M",
		"entityType": "AC"
	}, {
		"party": {
			"displayValue": "***624",
			"value": "D0F62A5CEC53EB985DBA69D5373F9BECFA40137819A3"
		},
		"requestType": "OTHERS",
		"requestData": "&#x7b;&quot;elements&quot;&#x3a;&#x5b;&#x7b;&quot;id&quot;&#x3a;&quot;SCH1&quot;,&quot;type&quot;&#x3a;&quot;SCH&quot;,&quot;label&quot;&#x3a;null,&quot;values&quot;&#x3a;&#x5b;&#x5d;,&quot;displayValues&quot;&#x3a;&#x5b;&#x5d;&#x7d;,&#x7b;&quot;id&quot;&#x3a;&quot;SBH2&quot;,&quot;type&quot;&#x3a;&quot;SBH&quot;,&quot;label&quot;&#x3a;null,&quot;values&quot;&#x3a;&#x5b;&#x5d;,&quot;displayValues&quot;&#x3a;&#x5b;&#x5d;&#x7d;,&#x7b;&quot;id&quot;&#x3a;&quot;FFTB3&quot;,&quot;type&quot;&#x3a;&quot;FFTB&quot;,&quot;label&quot;&#x3a;&quot;L1&quot;,&quot;values&quot;&#x3a;&#x5b;&#x5d;,&quot;displayValues&quot;&#x3a;&#x5b;&quot;&#x23;&quot;&#x5d;&#x7d;&#x5d;&#x7d;",
		"entityTypeIdentifier": "66667777888894339",
		"status": "PE",
		"priority": "M",
		"creationDate": "2018-04-30T10:07:38.000Z",
		"id": "421",
		"entityTypeIdentifierKey": "DE",
		"lastUpdatedDate": "2018-04-30T10:07:38.139Z",
		"definitionId": "SR0000000420",
		"product": "TD",
		"categoryType": "Term Deposit",
		"priorityType": "M",
		"entityType": "AC"
	}, {
		"party": {
			"displayValue": "***624",
			"value": "D0F62A5CEC53EB985DBA69D5373F9BECFA40137819A3"
		},
		"requestType": "OTHERS",
		"requestData": "&#x7b;&quot;elements&quot;&#x3a;&#x5b;&#x7b;&quot;id&quot;&#x3a;&quot;FFTB1&quot;,&quot;type&quot;&#x3a;&quot;FFTB&quot;,&quot;label&quot;&#x3a;&quot;Name&quot;,&quot;values&quot;&#x3a;&#x5b;&#x5d;,&quot;displayValues&quot;&#x3a;&#x5b;&quot;Rishabh&quot;&#x5d;&#x7d;,&#x7b;&quot;id&quot;&#x3a;&quot;FFRB2&quot;,&quot;type&quot;&#x3a;&quot;FFRB&quot;,&quot;label&quot;&#x3a;&quot;Citizenship&quot;,&quot;values&quot;&#x3a;&#x5b;&#x5d;,&quot;displayValues&quot;&#x3a;&#x5b;&quot;Resident&quot;&#x5d;&#x7d;,&#x7b;&quot;id&quot;&#x3a;&quot;FFMC3&quot;,&quot;type&quot;&#x3a;&quot;FFMC&quot;,&quot;label&quot;&#x3a;&quot;Identity types&quot;,&quot;values&quot;&#x3a;&#x5b;&#x5d;,&quot;displayValues&quot;&#x3a;&#x5b;&quot;aadhar&quot;&#x5d;&#x7d;,&#x7b;&quot;id&quot;&#x3a;&quot;FFDL4&quot;,&quot;type&quot;&#x3a;&quot;FFDL&quot;,&quot;label&quot;&#x3a;&quot;Country of residence&quot;,&quot;values&quot;&#x3a;&#x5b;&#x5d;,&quot;displayValues&quot;&#x3a;&#x5b;&quot;UK&quot;&#x5d;&#x7d;,&#x7b;&quot;id&quot;&#x3a;&quot;FFFU5&quot;,&quot;type&quot;&#x3a;&quot;FFFU&quot;,&quot;label&quot;&#x3a;&quot;Upload File&quot;,&quot;values&quot;&#x3a;&#x5b;&#x5d;,&quot;displayValues&quot;&#x3a;&#x5b;&#x5d;&#x7d;,&#x7b;&quot;id&quot;&#x3a;&quot;FFMS6&quot;,&quot;type&quot;&#x3a;&quot;FFMS&quot;,&quot;label&quot;&#x3a;&quot;Address Proof&quot;,&quot;values&quot;&#x3a;&#x5b;&#x5d;,&quot;displayValues&quot;&#x3a;&#x5b;&quot;aadhar&quot;&#x5d;&#x7d;,&#x7b;&quot;id&quot;&#x3a;&quot;PDAN7&quot;,&quot;type&quot;&#x3a;&quot;PDAN&quot;,&quot;label&quot;&#x3a;&quot;Funding Account&quot;,&quot;values&quot;&#x3a;&#x5b;&quot;BF26A47AB85F075FF3FA2BA3929232B316AE387E88FD2C2466A53133D4&quot;&#x5d;,&quot;displayValues&quot;&#x3a;&#x5b;&quot;xxxxxxxxxxxx0024&quot;&#x5d;&#x7d;,&#x7b;&quot;id&quot;&#x3a;&quot;PDAD8&quot;,&quot;type&quot;&#x3a;&quot;PDAD&quot;,&quot;label&quot;&#x3a;&quot;Account No Debit card&quot;,&quot;values&quot;&#x3a;&#x5b;&quot;BF26A47AB85F075FF3FA2BA0951E3601B2CEA8BB9AE45027DBDBF6948F&quot;&#x5d;,&quot;displayValues&quot;&#x3a;&#x5b;&quot;xxxxxxxxxxxx0013&quot;&#x5d;&#x7d;,&#x7b;&quot;id&quot;&#x3a;&quot;PDGS9&quot;,&quot;type&quot;&#x3a;&quot;PDGS&quot;,&quot;label&quot;&#x3a;&quot;Gender&quot;,&quot;values&quot;&#x3a;&#x5b;&quot;M&quot;&#x5d;,&quot;displayValues&quot;&#x3a;&#x5b;&quot;Male&quot;&#x5d;&#x7d;,&#x7b;&quot;id&quot;&#x3a;&quot;PDSS10&quot;,&quot;type&quot;&#x3a;&quot;PDSS&quot;,&quot;label&quot;&#x3a;&quot;Salutation&quot;,&quot;values&quot;&#x3a;&#x5b;&quot;87&quot;&#x5d;,&quot;displayValues&quot;&#x3a;&#x5b;&quot;Mr&quot;&#x5d;&#x7d;,&#x7b;&quot;id&quot;&#x3a;&quot;PDDP11&quot;,&quot;type&quot;&#x3a;&quot;PDDP&quot;,&quot;label&quot;&#x3a;&quot;DOB&quot;,&quot;values&quot;&#x3a;&#x5b;&#x5d;,&quot;displayValues&quot;&#x3a;&#x5b;&quot;1991-11-04&quot;&#x5d;&#x7d;&#x5d;&#x7d;",
		"entityTypeIdentifier": "66667777888894339",
		"status": "PE",
		"priority": "M",
		"creationDate": "2018-04-30T09:42:54.000Z",
		"id": "420",
		"entityTypeIdentifierKey": "DE",
		"lastUpdatedDate": "2018-04-30T09:42:54.995Z",
		"definitionId": "SR0000001729",
		"product": "demo1",
		"categoryType": "democat",
		"priorityType": "M",
		"entityType": "AC"
	}, {
		"party": {
			"displayValue": "***624",
			"value": "D0F62A5CEC53EB985DBA69D5373F9BECFA40137819A3"
		},
		"requestType": "OTHERS",
		"requestData": "&#x7b;&quot;elements&quot;&#x3a;&#x5b;&#x7b;&quot;id&quot;&#x3a;&quot;SCH1&quot;,&quot;type&quot;&#x3a;&quot;SCH&quot;,&quot;label&quot;&#x3a;null,&quot;values&quot;&#x3a;&#x5b;&#x5d;,&quot;displayValues&quot;&#x3a;&#x5b;&#x5d;&#x7d;,&#x7b;&quot;id&quot;&#x3a;&quot;SBH2&quot;,&quot;type&quot;&#x3a;&quot;SBH&quot;,&quot;label&quot;&#x3a;null,&quot;values&quot;&#x3a;&#x5b;&#x5d;,&quot;displayValues&quot;&#x3a;&#x5b;&#x5d;&#x7d;,&#x7b;&quot;id&quot;&#x3a;&quot;FFTB3&quot;,&quot;type&quot;&#x3a;&quot;FFTB&quot;,&quot;label&quot;&#x3a;&quot;L1&quot;,&quot;values&quot;&#x3a;&#x5b;&#x5d;,&quot;displayValues&quot;&#x3a;&#x5b;&quot;&#x5e;&amp;&#x24;&amp;&#x5e;&#x25;&#x2a;&#x5e;&quot;&#x5d;&#x7d;&#x5d;&#x7d;",
		"entityTypeIdentifier": "66667777888894339",
		"status": "CO",
		"priority": "M",
		"creationDate": "2018-04-30T06:51:00.000Z",
		"id": "417",
		"comments": "approved&#xa;",
		"entityTypeIdentifierKey": "DE",
		"lastUpdatedDate": "2018-04-30T08:39:54.191Z",
		"definitionId": "SR0000000420",
		"product": "TD",
		"categoryType": "Term Deposit",
		"priorityType": "M",
		"entityType": "AC"
	}, {
		"party": {
			"displayValue": "***624",
			"value": "D0F62A5CEC53EB985DBA69D5373F9BECFA40137819A3"
		},
		"requestType": "OTHERS",
		"requestData": "&#x7b;&quot;elements&quot;&#x3a;&#x5b;&#x7b;&quot;id&quot;&#x3a;&quot;SCH1&quot;,&quot;type&quot;&#x3a;&quot;SCH&quot;,&quot;label&quot;&#x3a;null,&quot;values&quot;&#x3a;&#x5b;&#x5d;,&quot;displayValues&quot;&#x3a;&#x5b;&#x5d;&#x7d;,&#x7b;&quot;id&quot;&#x3a;&quot;SBH2&quot;,&quot;type&quot;&#x3a;&quot;SBH&quot;,&quot;label&quot;&#x3a;null,&quot;values&quot;&#x3a;&#x5b;&#x5d;,&quot;displayValues&quot;&#x3a;&#x5b;&#x5d;&#x7d;,&#x7b;&quot;id&quot;&#x3a;&quot;FFTB3&quot;,&quot;type&quot;&#x3a;&quot;FFTB&quot;,&quot;label&quot;&#x3a;&quot;L1&quot;,&quot;values&quot;&#x3a;&#x5b;&#x5d;,&quot;displayValues&quot;&#x3a;&#x5b;&quot;&amp;&#x25;&amp;&#x25;&amp;&quot;&#x5d;&#x7d;&#x5d;&#x7d;",
		"entityTypeIdentifier": "66667777888894339",
		"status": "PE",
		"priority": "M",
		"creationDate": "2018-04-30T06:19:50.000Z",
		"id": "416",
		"entityTypeIdentifierKey": "DE",
		"lastUpdatedDate": "2018-04-30T06:19:50.473Z",
		"definitionId": "SR0000000420",
		"product": "TD",
		"categoryType": "Term Deposit",
		"priorityType": "M",
		"entityType": "AC"
	}, {
		"party": {
			"displayValue": "***624",
			"value": "D0F62A5CEC53EB985DBA69D5373F9BECFA40137819A3"
		},
		"requestType": "OTHERS",
		"requestData": "&#x7b;&quot;elements&quot;&#x3a;&#x5b;&#x7b;&quot;id&quot;&#x3a;&quot;SCH1&quot;,&quot;type&quot;&#x3a;&quot;SCH&quot;,&quot;label&quot;&#x3a;null,&quot;values&quot;&#x3a;&#x5b;&#x5d;,&quot;displayValues&quot;&#x3a;&#x5b;&#x5d;&#x7d;,&#x7b;&quot;id&quot;&#x3a;&quot;SBH2&quot;,&quot;type&quot;&#x3a;&quot;SBH&quot;,&quot;label&quot;&#x3a;null,&quot;values&quot;&#x3a;&#x5b;&#x5d;,&quot;displayValues&quot;&#x3a;&#x5b;&#x5d;&#x7d;,&#x7b;&quot;id&quot;&#x3a;&quot;FFTB3&quot;,&quot;type&quot;&#x3a;&quot;FFTB&quot;,&quot;label&quot;&#x3a;&quot;L1&quot;,&quot;values&quot;&#x3a;&#x5b;&#x5d;,&quot;displayValues&quot;&#x3a;&#x5b;&quot;&#x24;&#x25;&amp;&#x25;&amp;&#x25;&amp;&quot;&#x5d;&#x7d;&#x5d;&#x7d;",
		"entityTypeIdentifier": "66667777888894339",
		"status": "CO",
		"priority": "M",
		"creationDate": "2018-04-27T11:24:47.000Z",
		"id": "414",
		"comments": "service request status completed  that have created through definition form builder.service request status completed  that have created through definition form builder.service request status completed  that have created through definition form builder.",
		"entityTypeIdentifierKey": "DE",
		"lastUpdatedDate": "2018-04-27T11:28:51.243Z",
		"definitionId": "SR0000000420",
		"product": "TD",
		"categoryType": "Term Deposit",
		"priorityType": "M",
		"entityType": "AC"
	}, {
		"party": {
			"displayValue": "***624",
			"value": "D0F62A5CEC53EB985DBA69D5373F9BECFA40137819A3"
		},
		"requestType": "OTHERS",
		"requestData": "&#x7b;&quot;elements&quot;&#x3a;&#x5b;&#x7b;&quot;id&quot;&#x3a;&quot;FFTB1&quot;,&quot;type&quot;&#x3a;&quot;FFTB&quot;,&quot;label&quot;&#x3a;&quot;Name&quot;,&quot;values&quot;&#x3a;&#x5b;&#x5d;,&quot;displayValues&quot;&#x3a;&#x5b;&quot;Siddharth&quot;&#x5d;&#x7d;,&#x7b;&quot;id&quot;&#x3a;&quot;FFRB2&quot;,&quot;type&quot;&#x3a;&quot;FFRB&quot;,&quot;label&quot;&#x3a;&quot;Citizenship&quot;,&quot;values&quot;&#x3a;&#x5b;&#x5d;,&quot;displayValues&quot;&#x3a;&#x5b;&quot;Non Resident&quot;&#x5d;&#x7d;,&#x7b;&quot;id&quot;&#x3a;&quot;FFMC3&quot;,&quot;type&quot;&#x3a;&quot;FFMC&quot;,&quot;label&quot;&#x3a;&quot;Identity &quot;,&quot;values&quot;&#x3a;&#x5b;&#x5d;,&quot;displayValues&quot;&#x3a;&#x5b;&quot;Pan Card&quot;&#x5d;&#x7d;,&#x7b;&quot;id&quot;&#x3a;&quot;FFDL4&quot;,&quot;type&quot;&#x3a;&quot;FFDL&quot;,&quot;label&quot;&#x3a;&quot;Country of Residence&quot;,&quot;values&quot;&#x3a;&#x5b;&#x5d;,&quot;displayValues&quot;&#x3a;&#x5b;&quot;India&quot;&#x5d;&#x7d;,&#x7b;&quot;id&quot;&#x3a;&quot;PDSS10&quot;,&quot;type&quot;&#x3a;&quot;PDSS&quot;,&quot;label&quot;&#x3a;&quot;Salutation&quot;,&quot;values&quot;&#x3a;&#x5b;&quot;145&quot;&#x5d;,&quot;displayValues&quot;&#x3a;&#x5b;&quot;Other&quot;&#x5d;&#x7d;,&#x7b;&quot;id&quot;&#x3a;&quot;FFFU5&quot;,&quot;type&quot;&#x3a;&quot;FFFU&quot;,&quot;label&quot;&#x3a;&quot;Upload pic&quot;,&quot;values&quot;&#x3a;&#x5b;&quot;E2A00C135C2B68D604E6909D07F516EA4F4B05327D&quot;&#x5d;,&quot;displayValues&quot;&#x3a;&#x5b;&quot;deadpoolnew.jpg&quot;&#x5d;&#x7d;,&#x7b;&quot;id&quot;&#x3a;&quot;FFMS6&quot;,&quot;type&quot;&#x3a;&quot;FFMS&quot;,&quot;label&quot;&#x3a;&quot;Address Proof&quot;,&quot;values&quot;&#x3a;&#x5b;&#x5d;,&quot;displayValues&quot;&#x3a;&#x5b;&quot;Gas Bill&quot;&#x5d;&#x7d;,&#x7b;&quot;id&quot;&#x3a;&quot;PDAN7&quot;,&quot;type&quot;&#x3a;&quot;PDAN&quot;,&quot;label&quot;&#x3a;&quot;Funding Source&quot;,&quot;values&quot;&#x3a;&#x5b;&quot;91CC0E1A5F582EDB16A83E51434B2B3C07C6B77E505BB0AB77567A4D63&quot;&#x5d;,&quot;displayValues&quot;&#x3a;&#x5b;&quot;xxxxxxxxxxxx0024&quot;&#x5d;&#x7d;,&#x7b;&quot;id&quot;&#x3a;&quot;PDAD8&quot;,&quot;type&quot;&#x3a;&quot;PDAD&quot;,&quot;label&quot;&#x3a;&quot;Account No Debit Card&quot;,&quot;values&quot;&#x3a;&#x5b;&quot;91CC0E1A5F582EDB16A83E51434B2B3C07C6B77E505BB0AB77567A4D63&quot;&#x5d;,&quot;displayValues&quot;&#x3a;&#x5b;&quot;xxxxxxxxxxxx0024&quot;&#x5d;&#x7d;,&#x7b;&quot;id&quot;&#x3a;&quot;PDGS9&quot;,&quot;type&quot;&#x3a;&quot;PDGS&quot;,&quot;label&quot;&#x3a;&quot;Gender&quot;,&quot;values&quot;&#x3a;&#x5b;&quot;O&quot;&#x5d;,&quot;displayValues&quot;&#x3a;&#x5b;&quot;Other&quot;&#x5d;&#x7d;&#x5d;&#x7d;",
		"entityTypeIdentifier": "66667777888894339",
		"status": "PE",
		"priority": "M",
		"creationDate": "2018-04-27T10:12:37.000Z",
		"id": "413",
		"entityTypeIdentifierKey": "DE",
		"lastUpdatedDate": "2018-04-27T10:12:37.085Z",
		"definitionId": "SR0000001759",
		"product": "nehproduct",
		"categoryType": "nehrequest",
		"priorityType": "M",
		"entityType": "AC"
	}, {
		"party": {
			"displayValue": "***624",
			"value": "D0F62A5CEC53EB985DBA69D5373F9BECFA40137819A3"
		},
		"requestType": "OTHERS",
		"requestData": "&#x7b;&quot;elements&quot;&#x3a;&#x5b;&#x5d;&#x7d;",
		"entityTypeIdentifier": "66667777888894339",
		"status": "PE",
		"priority": "M",
		"creationDate": "2018-04-26T09:02:31.000Z",
		"id": "409",
		"entityTypeIdentifierKey": "DE",
		"lastUpdatedDate": "2018-04-26T09:02:31.990Z",
		"definitionId": "SR0000000719",
		"product": "CH",
		"categoryType": "OBDX Category",
		"priorityType": "M",
		"entityType": "AC"
	}, {
		"party": {
			"displayValue": "***624",
			"value": "D0F62A5CEC53EB985DBA69D5373F9BECFA40137819A3"
		},
		"requestType": "OTHERS",
		"requestData": "&#x7b;&quot;elements&quot;&#x3a;&#x5b;&#x7b;&quot;id&quot;&#x3a;&quot;SCH1&quot;,&quot;type&quot;&#x3a;&quot;SCH&quot;,&quot;label&quot;&#x3a;null,&quot;values&quot;&#x3a;&#x5b;&#x5d;,&quot;displayValues&quot;&#x3a;&#x5b;&#x5d;&#x7d;,&#x7b;&quot;id&quot;&#x3a;&quot;FFTB3&quot;,&quot;type&quot;&#x3a;&quot;FFTB&quot;,&quot;label&quot;&#x3a;&quot;Enter 2 Wheeler Loan Amount &quot;,&quot;values&quot;&#x3a;&#x5b;&#x5d;,&quot;displayValues&quot;&#x3a;&#x5b;&quot;2323232&quot;&#x5d;&#x7d;,&#x7b;&quot;id&quot;&#x3a;&quot;FFMC5&quot;,&quot;type&quot;&#x3a;&quot;FFMC&quot;,&quot;label&quot;&#x3a;&quot;Req Type&quot;,&quot;values&quot;&#x3a;&#x5b;&#x5d;,&quot;displayValues&quot;&#x3a;&#x5b;&quot;Immediate&quot;&#x5d;&#x7d;,&#x7b;&quot;id&quot;&#x3a;&quot;FFDL6&quot;,&quot;type&quot;&#x3a;&quot;FFDL&quot;,&quot;label&quot;&#x3a;&quot;Choose vehicle brand&quot;,&quot;values&quot;&#x3a;&#x5b;&#x5d;,&quot;displayValues&quot;&#x3a;&#x5b;&quot;TVS&quot;&#x5d;&#x7d;,&#x7b;&quot;id&quot;&#x3a;&quot;SCH2&quot;,&quot;type&quot;&#x3a;&quot;SCH&quot;,&quot;label&quot;&#x3a;null,&quot;values&quot;&#x3a;&#x5b;&#x5d;,&quot;displayValues&quot;&#x3a;&#x5b;&#x5d;&#x7d;,&#x7b;&quot;id&quot;&#x3a;&quot;FFTB4&quot;,&quot;type&quot;&#x3a;&quot;FFTB&quot;,&quot;label&quot;&#x3a;&quot;Enter 4 wheeler Loan Amount&quot;,&quot;values&quot;&#x3a;&#x5b;&#x5d;,&quot;displayValues&quot;&#x3a;&#x5b;&quot;2323&quot;&#x5d;&#x7d;,&#x7b;&quot;id&quot;&#x3a;&quot;FFDL7&quot;,&quot;type&quot;&#x3a;&quot;FFDL&quot;,&quot;label&quot;&#x3a;&quot;Choose 4 V brand&quot;,&quot;values&quot;&#x3a;&#x5b;&#x5d;,&quot;displayValues&quot;&#x3a;&#x5b;&quot;Maruti&quot;&#x5d;&#x7d;&#x5d;&#x7d;",
		"entityTypeIdentifier": "66667777888894339",
		"status": "PE",
		"priority": "M",
		"creationDate": "2018-04-25T12:27:48.000Z",
		"id": "408",
		"entityTypeIdentifierKey": "DE",
		"lastUpdatedDate": "2018-04-25T12:27:48.774Z",
		"definitionId": "SR0000001345",
		"product": "Loan",
		"categoryType": "Loan Topup",
		"priorityType": "M",
		"entityType": "AC"
	}, {
		"party": {
			"displayValue": "***624",
			"value": "D0F62A5CEC53EB985DBA69D5373F9BECFA40137819A3"
		},
		"requestType": "OTHERS",
		"requestData": "&#x7b;&quot;elements&quot;&#x3a;&#x5b;&#x7b;&quot;id&quot;&#x3a;&quot;PDSS9&quot;,&quot;type&quot;&#x3a;&quot;PDSS&quot;,&quot;label&quot;&#x3a;&quot;Select Salutation&quot;,&quot;values&quot;&#x3a;&#x5b;&quot;90&quot;&#x5d;,&quot;displayValues&quot;&#x3a;&#x5b;&quot;Ms&quot;&#x5d;&#x7d;,&#x7b;&quot;id&quot;&#x3a;&quot;FFTB2&quot;,&quot;type&quot;&#x3a;&quot;FFTB&quot;,&quot;label&quot;&#x3a;&quot;Name&quot;,&quot;values&quot;&#x3a;&#x5b;&#x5d;,&quot;displayValues&quot;&#x3a;&#x5b;&quot;XYZ&quot;&#x5d;&#x7d;,&#x7b;&quot;id&quot;&#x3a;&quot;PDGS8&quot;,&quot;type&quot;&#x3a;&quot;PDGS&quot;,&quot;label&quot;&#x3a;&quot;Select Gender&quot;,&quot;values&quot;&#x3a;&#x5b;&quot;F&quot;&#x5d;,&quot;displayValues&quot;&#x3a;&#x5b;&quot;Female&quot;&#x5d;&#x7d;,&#x7b;&quot;id&quot;&#x3a;&quot;FFMC4&quot;,&quot;type&quot;&#x3a;&quot;FFMC&quot;,&quot;label&quot;&#x3a;&quot;Income&quot;,&quot;values&quot;&#x3a;&#x5b;&#x5d;,&quot;displayValues&quot;&#x3a;&#x5b;&quot;200000&quot;&#x5d;&#x7d;,&#x7b;&quot;id&quot;&#x3a;&quot;FFRB3&quot;,&quot;type&quot;&#x3a;&quot;FFRB&quot;,&quot;label&quot;&#x3a;&quot;Applicant Type&quot;,&quot;values&quot;&#x3a;&#x5b;&#x5d;,&quot;displayValues&quot;&#x3a;&#x5b;&quot;Co app&quot;&#x5d;&#x7d;,&#x7b;&quot;id&quot;&#x3a;&quot;PDAN6&quot;,&quot;type&quot;&#x3a;&quot;PDAN&quot;,&quot;label&quot;&#x3a;&quot;Funding Source&quot;,&quot;values&quot;&#x3a;&#x5b;&quot;AT30016240024&quot;&#x5d;,&quot;displayValues&quot;&#x3a;&#x5b;&quot;xxxxxxxxxxxx0024&quot;&#x5d;&#x7d;,&#x7b;&quot;id&quot;&#x3a;&quot;FFDL5&quot;,&quot;type&quot;&#x3a;&quot;FFDL&quot;,&quot;label&quot;&#x3a;&quot;Occupation&quot;,&quot;values&quot;&#x3a;&#x5b;&#x5d;,&quot;displayValues&quot;&#x3a;&#x5b;&quot;Student&quot;&#x5d;&#x7d;&#x5d;&#x7d;",
		"entityTypeIdentifier": "66667777888894339",
		"status": "PE",
		"priority": "M",
		"creationDate": "2018-04-25T07:13:14.000Z",
		"id": "406",
		"entityTypeIdentifierKey": "DE",
		"lastUpdatedDate": "2018-04-25T07:13:14.651Z",
		"definitionId": "SR0000001420",
		"product": "Account",
		"categoryType": "Closure related",
		"priorityType": "M",
		"entityType": "AC"
	}, {
		"party": {
			"displayValue": "***624",
			"value": "D0F62A5CEC53EB985DBA69D5373F9BECFA40137819A3"
		},
		"requestType": "OTHERS",
		"requestData": "&#x7b;&quot;elements&quot;&#x3a;&#x5b;&#x7b;&quot;id&quot;&#x3a;&quot;SCH1&quot;,&quot;type&quot;&#x3a;&quot;SCH&quot;,&quot;label&quot;&#x3a;null,&quot;values&quot;&#x3a;&#x5b;&#x5d;,&quot;displayValues&quot;&#x3a;&#x5b;&#x5d;&#x7d;,&#x7b;&quot;id&quot;&#x3a;&quot;SBH2&quot;,&quot;type&quot;&#x3a;&quot;SBH&quot;,&quot;label&quot;&#x3a;null,&quot;values&quot;&#x3a;&#x5b;&#x5d;,&quot;displayValues&quot;&#x3a;&#x5b;&#x5d;&#x7d;,&#x7b;&quot;id&quot;&#x3a;&quot;FFTB3&quot;,&quot;type&quot;&#x3a;&quot;FFTB&quot;,&quot;label&quot;&#x3a;&quot;L1&quot;,&quot;values&quot;&#x3a;&#x5b;&#x5d;,&quot;displayValues&quot;&#x3a;&#x5b;&quot;&#x24;&#x25;&#x25;&#x25;&#x5e;&quot;&#x5d;&#x7d;&#x5d;&#x7d;",
		"entityTypeIdentifier": "66667777888894339",
		"status": "PE",
		"priority": "M",
		"creationDate": "2018-04-25T06:56:14.000Z",
		"id": "405",
		"entityTypeIdentifierKey": "DE",
		"lastUpdatedDate": "2018-04-25T06:56:14.417Z",
		"definitionId": "SR0000000420",
		"product": "TD",
		"categoryType": "Term Deposit",
		"priorityType": "M",
		"entityType": "AC"
	}, {
		"party": {
			"displayValue": "***624",
			"value": "D0F62A5CEC53EB985DBA69D5373F9BECFA40137819A3"
		},
		"requestType": "OTHERS",
		"requestData": "&#x7b;&quot;elements&quot;&#x3a;&#x5b;&#x7b;&quot;id&quot;&#x3a;&quot;FFTB1&quot;,&quot;type&quot;&#x3a;&quot;FFTB&quot;,&quot;label&quot;&#x3a;&quot;Name&quot;,&quot;values&quot;&#x3a;&#x5b;&#x5d;,&quot;displayValues&quot;&#x3a;&#x5b;&quot;Siddharth&quot;&#x5d;&#x7d;,&#x7b;&quot;id&quot;&#x3a;&quot;FFRB2&quot;,&quot;type&quot;&#x3a;&quot;FFRB&quot;,&quot;label&quot;&#x3a;&quot;Citizenship&quot;,&quot;values&quot;&#x3a;&#x5b;&#x5d;,&quot;displayValues&quot;&#x3a;&#x5b;&quot;Non Resident&quot;&#x5d;&#x7d;,&#x7b;&quot;id&quot;&#x3a;&quot;FFMC3&quot;,&quot;type&quot;&#x3a;&quot;FFMC&quot;,&quot;label&quot;&#x3a;&quot;Identity &quot;,&quot;values&quot;&#x3a;&#x5b;&#x5d;,&quot;displayValues&quot;&#x3a;&#x5b;&quot;Aadhar&quot;&#x5d;&#x7d;,&#x7b;&quot;id&quot;&#x3a;&quot;FFDL4&quot;,&quot;type&quot;&#x3a;&quot;FFDL&quot;,&quot;label&quot;&#x3a;&quot;Country of Residence&quot;,&quot;values&quot;&#x3a;&#x5b;&#x5d;,&quot;displayValues&quot;&#x3a;&#x5b;&quot;India&quot;&#x5d;&#x7d;,&#x7b;&quot;id&quot;&#x3a;&quot;PDSS10&quot;,&quot;type&quot;&#x3a;&quot;PDSS&quot;,&quot;label&quot;&#x3a;&quot;Salutation&quot;,&quot;values&quot;&#x3a;&#x5b;&quot;87&quot;&#x5d;,&quot;displayValues&quot;&#x3a;&#x5b;&quot;Mr&quot;&#x5d;&#x7d;,&#x7b;&quot;id&quot;&#x3a;&quot;FFFU5&quot;,&quot;type&quot;&#x3a;&quot;FFFU&quot;,&quot;label&quot;&#x3a;&quot;Upload pic&quot;,&quot;values&quot;&#x3a;&#x5b;&quot;26985&quot;&#x5d;,&quot;displayValues&quot;&#x3a;&#x5b;&quot;deadpool.jpg&quot;&#x5d;&#x7d;,&#x7b;&quot;id&quot;&#x3a;&quot;FFMS6&quot;,&quot;type&quot;&#x3a;&quot;FFMS&quot;,&quot;label&quot;&#x3a;&quot;Address Proof&quot;,&quot;values&quot;&#x3a;&#x5b;&#x5d;,&quot;displayValues&quot;&#x3a;&#x5b;&quot;Utlility Bill&quot;&#x5d;&#x7d;,&#x7b;&quot;id&quot;&#x3a;&quot;PDAN7&quot;,&quot;type&quot;&#x3a;&quot;PDAN&quot;,&quot;label&quot;&#x3a;&quot;Funding Source&quot;,&quot;values&quot;&#x3a;&#x5b;&quot;AT30016240024&quot;&#x5d;,&quot;displayValues&quot;&#x3a;&#x5b;&quot;xxxxxxxxxxxx0024&quot;&#x5d;&#x7d;,&#x7b;&quot;id&quot;&#x3a;&quot;PDAD8&quot;,&quot;type&quot;&#x3a;&quot;PDAD&quot;,&quot;label&quot;&#x3a;&quot;Account No Debit Card&quot;,&quot;values&quot;&#x3a;&#x5b;&quot;AT30016240013&quot;&#x5d;,&quot;displayValues&quot;&#x3a;&#x5b;&#x5d;&#x7d;,&#x7b;&quot;id&quot;&#x3a;&quot;PDGS9&quot;,&quot;type&quot;&#x3a;&quot;PDGS&quot;,&quot;label&quot;&#x3a;&quot;Gender&quot;,&quot;values&quot;&#x3a;&#x5b;&quot;M&quot;&#x5d;,&quot;displayValues&quot;&#x3a;&#x5b;&quot;Male&quot;&#x5d;&#x7d;&#x5d;&#x7d;",
		"entityTypeIdentifier": "66667777888894339",
		"status": "PE",
		"priority": "M",
		"creationDate": "2018-04-25T06:55:49.000Z",
		"id": "404",
		"entityTypeIdentifierKey": "DE",
		"lastUpdatedDate": "2018-04-25T06:55:49.048Z",
		"definitionId": "SR0000001759",
		"product": "nehproduct",
		"categoryType": "nehrequest",
		"priorityType": "M",
		"entityType": "AC"
	}, {
		"party": {
			"displayValue": "***624",
			"value": "D0F62A5CEC53EB985DBA69D5373F9BECFA40137819A3"
		},
		"requestType": "OTHERS",
		"requestData": "&#x7b;&quot;elements&quot;&#x3a;&#x5b;&#x7b;&quot;id&quot;&#x3a;&quot;PDSS5&quot;,&quot;type&quot;&#x3a;&quot;PDSS&quot;,&quot;label&quot;&#x3a;&quot;Salutation&quot;,&quot;values&quot;&#x3a;&#x5b;&quot;87&quot;&#x5d;,&quot;displayValues&quot;&#x3a;&#x5b;&quot;Mr&quot;&#x5d;&#x7d;,&#x7b;&quot;id&quot;&#x3a;&quot;FFTB1&quot;,&quot;type&quot;&#x3a;&quot;FFTB&quot;,&quot;label&quot;&#x3a;&quot;Name&quot;,&quot;values&quot;&#x3a;&#x5b;&#x5d;,&quot;displayValues&quot;&#x3a;&#x5b;&quot;ABC&quot;&#x5d;&#x7d;,&#x7b;&quot;id&quot;&#x3a;&quot;FFRB2&quot;,&quot;type&quot;&#x3a;&quot;FFRB&quot;,&quot;label&quot;&#x3a;&quot;Citizenship&quot;,&quot;values&quot;&#x3a;&#x5b;&#x5d;,&quot;displayValues&quot;&#x3a;&#x5b;&quot;NRI&quot;&#x5d;&#x7d;,&#x7b;&quot;id&quot;&#x3a;&quot;FFTB6&quot;,&quot;type&quot;&#x3a;&quot;FFTB&quot;,&quot;label&quot;&#x3a;&quot;Age&quot;,&quot;values&quot;&#x3a;&#x5b;&#x5d;,&quot;displayValues&quot;&#x3a;&#x5b;&quot;25&quot;&#x5d;&#x7d;,&#x7b;&quot;id&quot;&#x3a;&quot;FFMC3&quot;,&quot;type&quot;&#x3a;&quot;FFMC&quot;,&quot;label&quot;&#x3a;&quot;Identity types&quot;,&quot;values&quot;&#x3a;&#x5b;&#x5d;,&quot;displayValues&quot;&#x3a;&#x5b;&quot;passport&quot;&#x5d;&#x7d;,&#x7b;&quot;id&quot;&#x3a;&quot;PDAN4&quot;,&quot;type&quot;&#x3a;&quot;PDAN&quot;,&quot;label&quot;&#x3a;&quot;funding Account&quot;,&quot;values&quot;&#x3a;&#x5b;&quot;AT30016240024&quot;&#x5d;,&quot;displayValues&quot;&#x3a;&#x5b;&quot;xxxxxxxxxxxx0024&quot;&#x5d;&#x7d;,&#x7b;&quot;id&quot;&#x3a;&quot;FFMC7&quot;,&quot;type&quot;&#x3a;&quot;FFMC&quot;,&quot;label&quot;&#x3a;&quot;Choose values&quot;,&quot;values&quot;&#x3a;&#x5b;&#x5d;,&quot;displayValues&quot;&#x3a;&#x5b;&quot;passport&quot;&#x5d;&#x7d;&#x5d;&#x7d;",
		"entityTypeIdentifier": "66667777888894339",
		"status": "PE",
		"priority": "M",
		"creationDate": "2018-04-25T06:27:55.000Z",
		"id": "403",
		"entityTypeIdentifierKey": "DE",
		"lastUpdatedDate": "2018-04-25T06:27:55.680Z",
		"definitionId": "SR0000002197",
		"product": "LoanOrigin",
		"categoryType": "LoanReq",
		"priorityType": "M",
		"entityType": "AC"
	}, {
		"party": {
			"displayValue": "***624",
			"value": "D0F62A5CEC53EB985DBA69D5373F9BECFA40137819A3"
		},
		"requestType": "OTHERS",
		"requestData": "&#x7b;&quot;elements&quot;&#x3a;&#x5b;&#x7b;&quot;id&quot;&#x3a;&quot;FFTB1&quot;,&quot;type&quot;&#x3a;&quot;FFTB&quot;,&quot;label&quot;&#x3a;&quot;Name&quot;,&quot;values&quot;&#x3a;&#x5b;&#x5d;,&quot;displayValues&quot;&#x3a;&#x5b;&quot;Siddharth&quot;&#x5d;&#x7d;,&#x7b;&quot;id&quot;&#x3a;&quot;FFRB2&quot;,&quot;type&quot;&#x3a;&quot;FFRB&quot;,&quot;label&quot;&#x3a;&quot;Citizenship&quot;,&quot;values&quot;&#x3a;&#x5b;&#x5d;,&quot;displayValues&quot;&#x3a;&#x5b;&quot;Non Resident&quot;&#x5d;&#x7d;,&#x7b;&quot;id&quot;&#x3a;&quot;FFMC3&quot;,&quot;type&quot;&#x3a;&quot;FFMC&quot;,&quot;label&quot;&#x3a;&quot;Identity &quot;,&quot;values&quot;&#x3a;&#x5b;&#x5d;,&quot;displayValues&quot;&#x3a;&#x5b;&quot;Pan Card&quot;&#x5d;&#x7d;,&#x7b;&quot;id&quot;&#x3a;&quot;FFDL4&quot;,&quot;type&quot;&#x3a;&quot;FFDL&quot;,&quot;label&quot;&#x3a;&quot;Country of Residence&quot;,&quot;values&quot;&#x3a;&#x5b;&#x5d;,&quot;displayValues&quot;&#x3a;&#x5b;&quot;India&quot;&#x5d;&#x7d;,&#x7b;&quot;id&quot;&#x3a;&quot;PDSS10&quot;,&quot;type&quot;&#x3a;&quot;PDSS&quot;,&quot;label&quot;&#x3a;&quot;Salutation&quot;,&quot;values&quot;&#x3a;&#x5b;&quot;87&quot;&#x5d;,&quot;displayValues&quot;&#x3a;&#x5b;&quot;Mr&quot;&#x5d;&#x7d;,&#x7b;&quot;id&quot;&#x3a;&quot;FFFU5&quot;,&quot;type&quot;&#x3a;&quot;FFFU&quot;,&quot;label&quot;&#x3a;&quot;Upload pic&quot;,&quot;values&quot;&#x3a;&#x5b;&quot;26960&quot;&#x5d;,&quot;displayValues&quot;&#x3a;&#x5b;&quot;deadpool.jpg&quot;&#x5d;&#x7d;,&#x7b;&quot;id&quot;&#x3a;&quot;FFMS6&quot;,&quot;type&quot;&#x3a;&quot;FFMS&quot;,&quot;label&quot;&#x3a;&quot;Address Proof&quot;,&quot;values&quot;&#x3a;&#x5b;&#x5d;,&quot;displayValues&quot;&#x3a;&#x5b;&quot;Utlility Bill&quot;&#x5d;&#x7d;,&#x7b;&quot;id&quot;&#x3a;&quot;PDAN7&quot;,&quot;type&quot;&#x3a;&quot;PDAN&quot;,&quot;label&quot;&#x3a;&quot;Funding Source&quot;,&quot;values&quot;&#x3a;&#x5b;&quot;AT30016240013&quot;&#x5d;,&quot;displayValues&quot;&#x3a;&#x5b;&quot;xxxxxxxxxxxx0013&quot;&#x5d;&#x7d;,&#x7b;&quot;id&quot;&#x3a;&quot;PDAD8&quot;,&quot;type&quot;&#x3a;&quot;PDAD&quot;,&quot;label&quot;&#x3a;&quot;Account No Debit Card&quot;,&quot;values&quot;&#x3a;&#x5b;&quot;AT30016240013&quot;&#x5d;,&quot;displayValues&quot;&#x3a;&#x5b;&#x5d;&#x7d;,&#x7b;&quot;id&quot;&#x3a;&quot;PDGS9&quot;,&quot;type&quot;&#x3a;&quot;PDGS&quot;,&quot;label&quot;&#x3a;&quot;Gender&quot;,&quot;values&quot;&#x3a;&#x5b;&quot;M&quot;&#x5d;,&quot;displayValues&quot;&#x3a;&#x5b;&quot;Male&quot;&#x5d;&#x7d;&#x5d;&#x7d;",
		"entityTypeIdentifier": "66667777888894339",
		"status": "PE",
		"priority": "M",
		"creationDate": "2018-04-25T06:20:19.000Z",
		"id": "402",
		"entityTypeIdentifierKey": "DE",
		"lastUpdatedDate": "2018-04-25T06:20:19.289Z",
		"definitionId": "SR0000001759",
		"product": "nehproduct",
		"categoryType": "nehrequest",
		"priorityType": "M",
		"entityType": "AC"
	}, {
		"party": {
			"displayValue": "***624",
			"value": "D0F62A5CEC53EB985DBA69D5373F9BECFA40137819A3"
		},
		"requestType": "OTHERS",
		"requestData": "&#x7b;&quot;elements&quot;&#x3a;&#x5b;&#x7b;&quot;id&quot;&#x3a;&quot;PDSS9&quot;,&quot;type&quot;&#x3a;&quot;PDSS&quot;,&quot;label&quot;&#x3a;&quot;Select Salutation&quot;,&quot;values&quot;&#x3a;&#x5b;&quot;145&quot;&#x5d;&#x7d;,&#x7b;&quot;id&quot;&#x3a;&quot;FFTB2&quot;,&quot;type&quot;&#x3a;&quot;FFTB&quot;,&quot;label&quot;&#x3a;&quot;Name&quot;,&quot;values&quot;&#x3a;&#x5b;&quot;abc&quot;&#x5d;&#x7d;,&#x7b;&quot;id&quot;&#x3a;&quot;PDGS8&quot;,&quot;type&quot;&#x3a;&quot;PDGS&quot;,&quot;label&quot;&#x3a;&quot;Select Gender&quot;,&quot;values&quot;&#x3a;&#x5b;&quot;M&quot;&#x5d;&#x7d;,&#x7b;&quot;id&quot;&#x3a;&quot;FFMC4&quot;,&quot;type&quot;&#x3a;&quot;FFMC&quot;,&quot;label&quot;&#x3a;&quot;Income&quot;,&quot;values&quot;&#x3a;&#x5b;&quot;10000&quot;&#x5d;&#x7d;,&#x7b;&quot;id&quot;&#x3a;&quot;FFRB3&quot;,&quot;type&quot;&#x3a;&quot;FFRB&quot;,&quot;label&quot;&#x3a;&quot;Applicant Type&quot;,&quot;values&quot;&#x3a;&#x5b;&quot;Co app&quot;&#x5d;&#x7d;,&#x7b;&quot;id&quot;&#x3a;&quot;PDAN6&quot;,&quot;type&quot;&#x3a;&quot;PDAN&quot;,&quot;label&quot;&#x3a;&quot;Funding Source&quot;,&quot;values&quot;&#x3a;&#x5b;&quot;046639D6D8E8FAB6E34B78FFD9A8A02128FF80D842D95CFB9C96C40DFC&quot;&#x5d;&#x7d;,&#x7b;&quot;id&quot;&#x3a;&quot;FFDL5&quot;,&quot;type&quot;&#x3a;&quot;FFDL&quot;,&quot;label&quot;&#x3a;&quot;Occupation&quot;,&quot;values&quot;&#x3a;&#x5b;&quot;Student&quot;&#x5d;&#x7d;&#x5d;&#x7d;",
		"entityTypeIdentifier": "66667777888894339",
		"status": "PE",
		"priority": "M",
		"creationDate": "2018-04-24T07:05:32.000Z",
		"id": "401",
		"entityTypeIdentifierKey": "DE",
		"lastUpdatedDate": "2018-04-24T07:05:32.854Z",
		"definitionId": "SR0000001420",
		"product": "Account",
		"categoryType": "Closure related",
		"priorityType": "M",
		"entityType": "AC"
	}, {
		"party": {
			"displayValue": "***624",
			"value": "D0F62A5CEC53EB985DBA69D5373F9BECFA40137819A3"
		},
		"requestType": "OTHERS",
		"requestData": "&#x7b;&quot;elements&quot;&#x3a;&#x5b;&#x7b;&quot;id&quot;&#x3a;&quot;FFTB1&quot;,&quot;type&quot;&#x3a;&quot;FFTB&quot;,&quot;label&quot;&#x3a;&quot;Name&quot;,&quot;values&quot;&#x3a;&#x5b;&quot;Demo User&quot;&#x5d;&#x7d;,&#x7b;&quot;id&quot;&#x3a;&quot;FFRB2&quot;,&quot;type&quot;&#x3a;&quot;FFRB&quot;,&quot;label&quot;&#x3a;&quot;Citizenship&quot;,&quot;values&quot;&#x3a;&#x5b;&quot;Resident&quot;&#x5d;&#x7d;,&#x7b;&quot;id&quot;&#x3a;&quot;FFMC3&quot;,&quot;type&quot;&#x3a;&quot;FFMC&quot;,&quot;label&quot;&#x3a;&quot;Identity &quot;,&quot;values&quot;&#x3a;&#x5b;&quot;Pan Card&quot;,&quot;Aadhar&quot;&#x5d;&#x7d;,&#x7b;&quot;id&quot;&#x3a;&quot;FFDL4&quot;,&quot;type&quot;&#x3a;&quot;FFDL&quot;,&quot;label&quot;&#x3a;&quot;Country of Residence&quot;,&quot;values&quot;&#x3a;&#x5b;&quot;US&quot;&#x5d;&#x7d;,&#x7b;&quot;id&quot;&#x3a;&quot;PDSS10&quot;,&quot;type&quot;&#x3a;&quot;PDSS&quot;,&quot;label&quot;&#x3a;&quot;Salutation&quot;,&quot;values&quot;&#x3a;&#x5b;&quot;145&quot;&#x5d;&#x7d;,&#x7b;&quot;id&quot;&#x3a;&quot;FFFU5&quot;,&quot;type&quot;&#x3a;&quot;FFFU&quot;,&quot;label&quot;&#x3a;&quot;Upload pic&quot;,&quot;values&quot;&#x3a;&#x5b;&quot;7AF0BC44D27CA26A38C3227E48003D37EEC6C43BE0&quot;,&quot;traincomponentcode.png&quot;&#x5d;&#x7d;,&#x7b;&quot;id&quot;&#x3a;&quot;FFMS6&quot;,&quot;type&quot;&#x3a;&quot;FFMS&quot;,&quot;label&quot;&#x3a;&quot;Address Proof&quot;,&quot;values&quot;&#x3a;&#x5b;&quot;Utlility Bill&quot;&#x5d;&#x7d;,&#x7b;&quot;id&quot;&#x3a;&quot;PDAN7&quot;,&quot;type&quot;&#x3a;&quot;PDAN&quot;,&quot;label&quot;&#x3a;&quot;Funding Source&quot;,&quot;values&quot;&#x3a;&#x5b;&quot;0992BA4DD3D4472C13ED55A43973E9605EF1ACB9BE67BEB8F8262C2488&quot;&#x5d;&#x7d;,&#x7b;&quot;id&quot;&#x3a;&quot;PDAD8&quot;,&quot;type&quot;&#x3a;&quot;PDAD&quot;,&quot;label&quot;&#x3a;&quot;Account No Debit Card&quot;,&quot;values&quot;&#x3a;&#x5b;&quot;0992BA4DD3D4472C13ED55A73E9B3FBF12328C43913437311FD12FB0CB&quot;&#x5d;&#x7d;,&#x7b;&quot;id&quot;&#x3a;&quot;PDGS9&quot;,&quot;type&quot;&#x3a;&quot;PDGS&quot;,&quot;label&quot;&#x3a;&quot;Gender&quot;,&quot;values&quot;&#x3a;&#x5b;&quot;F&quot;&#x5d;&#x7d;&#x5d;&#x7d;",
		"entityTypeIdentifier": "66667777888894339",
		"status": "PE",
		"priority": "M",
		"creationDate": "2018-04-20T12:18:04.000Z",
		"id": "371",
		"entityTypeIdentifierKey": "DE",
		"lastUpdatedDate": "2018-04-20T12:18:04.078Z",
		"definitionId": "SR0000001759",
		"product": "nehproduct",
		"categoryType": "nehrequest",
		"priorityType": "M",
		"entityType": "AC"
	}, {
		"party": {
			"displayValue": "***624",
			"value": "D0F62A5CEC53EB985DBA69D5373F9BECFA40137819A3"
		},
		"requestType": "OTHERS",
		"requestData": "&#x7b;&quot;elements&quot;&#x3a;&#x5b;&#x7b;&quot;id&quot;&#x3a;&quot;SCH1&quot;,&quot;type&quot;&#x3a;&quot;SCH&quot;,&quot;label&quot;&#x3a;null,&quot;values&quot;&#x3a;&#x5b;&#x5d;&#x7d;,&#x7b;&quot;id&quot;&#x3a;&quot;FFTB3&quot;,&quot;type&quot;&#x3a;&quot;FFTB&quot;,&quot;label&quot;&#x3a;&quot;Enter 2 Wheeler Loan Amount &quot;,&quot;values&quot;&#x3a;&#x5b;&quot;555&quot;&#x5d;&#x7d;,&#x7b;&quot;id&quot;&#x3a;&quot;FFMC5&quot;,&quot;type&quot;&#x3a;&quot;FFMC&quot;,&quot;label&quot;&#x3a;&quot;Req Type&quot;,&quot;values&quot;&#x3a;&#x5b;&quot;Immediate&quot;&#x5d;&#x7d;,&#x7b;&quot;id&quot;&#x3a;&quot;FFDL6&quot;,&quot;type&quot;&#x3a;&quot;FFDL&quot;,&quot;label&quot;&#x3a;&quot;Choose vehicle brand&quot;,&quot;values&quot;&#x3a;&#x5b;&quot;TVS&quot;&#x5d;&#x7d;,&#x7b;&quot;id&quot;&#x3a;&quot;SCH2&quot;,&quot;type&quot;&#x3a;&quot;SCH&quot;,&quot;label&quot;&#x3a;null,&quot;values&quot;&#x3a;&#x5b;&#x5d;&#x7d;,&#x7b;&quot;id&quot;&#x3a;&quot;FFTB4&quot;,&quot;type&quot;&#x3a;&quot;FFTB&quot;,&quot;label&quot;&#x3a;&quot;Enter 4 wheeler Loan Amount&quot;,&quot;values&quot;&#x3a;&#x5b;&quot;444&quot;&#x5d;&#x7d;,&#x7b;&quot;id&quot;&#x3a;&quot;FFDL7&quot;,&quot;type&quot;&#x3a;&quot;FFDL&quot;,&quot;label&quot;&#x3a;&quot;Choose 4 V brand&quot;,&quot;values&quot;&#x3a;&#x5b;&quot;Honda&quot;&#x5d;&#x7d;&#x5d;&#x7d;",
		"entityTypeIdentifier": "66667777888894339",
		"status": "PE",
		"priority": "M",
		"creationDate": "2018-04-20T11:27:22.000Z",
		"id": "370",
		"entityTypeIdentifierKey": "DE",
		"lastUpdatedDate": "2018-04-20T11:27:22.808Z",
		"definitionId": "SR0000001345",
		"product": "Loan",
		"categoryType": "Loan Topup",
		"priorityType": "M",
		"entityType": "AC"
	}, {
		"party": {
			"displayValue": "***624",
			"value": "D0F62A5CEC53EB985DBA69D5373F9BECFA40137819A3"
		},
		"requestType": "OTHERS",
		"requestData": "&#x7b;&quot;elements&quot;&#x3a;&#x5b;&#x7b;&quot;id&quot;&#x3a;&quot;FFTB1&quot;,&quot;type&quot;&#x3a;&quot;FFTB&quot;,&quot;label&quot;&#x3a;&quot;Name&quot;,&quot;values&quot;&#x3a;&#x5b;&quot;ABC&quot;&#x5d;&#x7d;,&#x7b;&quot;id&quot;&#x3a;&quot;FFRB2&quot;,&quot;type&quot;&#x3a;&quot;FFRB&quot;,&quot;label&quot;&#x3a;&quot;Citizenship&quot;,&quot;values&quot;&#x3a;&#x5b;&quot;Resident&quot;&#x5d;&#x7d;,&#x7b;&quot;id&quot;&#x3a;&quot;FFMC3&quot;,&quot;type&quot;&#x3a;&quot;FFMC&quot;,&quot;label&quot;&#x3a;&quot;Identity &quot;,&quot;values&quot;&#x3a;&#x5b;&quot;Aadhar&quot;&#x5d;&#x7d;,&#x7b;&quot;id&quot;&#x3a;&quot;FFDL4&quot;,&quot;type&quot;&#x3a;&quot;FFDL&quot;,&quot;label&quot;&#x3a;&quot;Country of Residence&quot;,&quot;values&quot;&#x3a;&#x5b;&quot;India&quot;&#x5d;&#x7d;,&#x7b;&quot;id&quot;&#x3a;&quot;PDSS10&quot;,&quot;type&quot;&#x3a;&quot;PDSS&quot;,&quot;label&quot;&#x3a;&quot;Salutation&quot;,&quot;values&quot;&#x3a;&#x5b;&quot;90&quot;&#x5d;&#x7d;,&#x7b;&quot;id&quot;&#x3a;&quot;FFFU5&quot;,&quot;type&quot;&#x3a;&quot;FFFU&quot;,&quot;label&quot;&#x3a;&quot;Upload pic&quot;,&quot;values&quot;&#x3a;&#x5b;&quot;26509&quot;,&quot;image2017-12-26 17_11_45.png&quot;&#x5d;&#x7d;,&#x7b;&quot;id&quot;&#x3a;&quot;FFMS6&quot;,&quot;type&quot;&#x3a;&quot;FFMS&quot;,&quot;label&quot;&#x3a;&quot;Address Proof&quot;,&quot;values&quot;&#x3a;&#x5b;&quot;Utlility Bill&quot;&#x5d;&#x7d;,&#x7b;&quot;id&quot;&#x3a;&quot;PDAN7&quot;,&quot;type&quot;&#x3a;&quot;PDAN&quot;,&quot;label&quot;&#x3a;&quot;Funding Source&quot;,&quot;values&quot;&#x3a;&#x5b;&quot;69A3A7BE6FD267A233A5839D791411B20901FBBE4CC7CE48531E60FD44&quot;&#x5d;&#x7d;,&#x7b;&quot;id&quot;&#x3a;&quot;PDAD8&quot;,&quot;type&quot;&#x3a;&quot;PDAD&quot;,&quot;label&quot;&#x3a;&quot;Account No Debit Card&quot;,&quot;values&quot;&#x3a;&#x5b;&#x5d;&#x7d;,&#x7b;&quot;id&quot;&#x3a;&quot;PDGS9&quot;,&quot;type&quot;&#x3a;&quot;PDGS&quot;,&quot;label&quot;&#x3a;&quot;Gender&quot;,&quot;values&quot;&#x3a;&#x5b;&quot;F&quot;&#x5d;&#x7d;&#x5d;&#x7d;",
		"entityTypeIdentifier": "66667777888894339",
		"status": "PE",
		"priority": "M",
		"creationDate": "2018-04-20T06:12:48.000Z",
		"id": "365",
		"entityTypeIdentifierKey": "DE",
		"lastUpdatedDate": "2018-04-20T06:12:48.170Z",
		"definitionId": "SR0000001759",
		"product": "nehproduct",
		"categoryType": "nehrequest",
		"priorityType": "M",
		"entityType": "AC"
	}, {
		"party": {
			"displayValue": "***624",
			"value": "D0F62A5CEC53EB985DBA69D5373F9BECFA40137819A3"
		},
		"requestType": "OTHERS",
		"requestData": "&#x7b;&quot;elements&quot;&#x3a;&#x5b;&#x7b;&quot;id&quot;&#x3a;&quot;FFDL1&quot;,&quot;type&quot;&#x3a;&quot;FFDL&quot;,&quot;label&quot;&#x3a;&quot;Drop list&quot;,&quot;values&quot;&#x3a;&#x5b;&quot;value3&quot;&#x5d;&#x7d;&#x5d;&#x7d;",
		"entityTypeIdentifier": "66667777888894339",
		"status": "PE",
		"priority": "M",
		"creationDate": "2018-04-19T13:38:33.000Z",
		"id": "360",
		"entityTypeIdentifierKey": "DE",
		"lastUpdatedDate": "2018-04-19T13:38:33.784Z",
		"definitionId": "SR0000001266",
		"product": "Credit Card",
		"categoryType": "Credit Card Payment",
		"priorityType": "M",
		"entityType": "AC"
	}, {
		"party": {
			"displayValue": "***624",
			"value": "D0F62A5CEC53EB985DBA69D5373F9BECFA40137819A3"
		},
		"requestType": "OTHERS",
		"requestData": "&#x7b;&quot;elements&quot;&#x3a;&#x5b;&#x7b;&quot;id&quot;&#x3a;&quot;FFDL1&quot;,&quot;type&quot;&#x3a;&quot;FFDL&quot;,&quot;label&quot;&#x3a;&quot;Drop list&quot;,&quot;values&quot;&#x3a;&#x5b;&quot;value2&quot;&#x5d;&#x7d;&#x5d;&#x7d;",
		"entityTypeIdentifier": "66667777888894339",
		"status": "PE",
		"priority": "M",
		"creationDate": "2018-04-18T14:33:15.000Z",
		"id": "322",
		"entityTypeIdentifierKey": "DE",
		"lastUpdatedDate": "2018-04-18T14:33:15.591Z",
		"definitionId": "SR0000001266",
		"product": "Credit Card",
		"categoryType": "Credit Card Payment",
		"priorityType": "M",
		"entityType": "AC"
	}, {
		"party": {
			"displayValue": "***624",
			"value": "D0F62A5CEC53EB985DBA69D5373F9BECFA40137819A3"
		},
		"requestType": "OTHERS",
		"requestData": "&#x7b;&quot;elements&quot;&#x3a;&#x5b;&#x7b;&quot;id&quot;&#x3a;&quot;PDAD1&quot;,&quot;type&quot;&#x3a;&quot;PDAD&quot;,&quot;label&quot;&#x3a;&quot;Card&quot;,&quot;values&quot;&#x3a;&#x5b;&quot;ECC870CEDCFE9280409B528A8A2AB1FF4D96494B85291CC631E28CC460&quot;&#x5d;&#x7d;&#x5d;&#x7d;",
		"entityTypeIdentifier": "66667777888894339",
		"status": "PE",
		"priority": "M",
		"creationDate": "2018-04-18T09:59:23.000Z",
		"id": "321",
		"entityTypeIdentifierKey": "DE",
		"lastUpdatedDate": "2018-04-18T09:59:23.945Z",
		"definitionId": "SR0000001451",
		"product": "Debit Card",
		"categoryType": "Debit Card Pin Related",
		"priorityType": "M",
		"entityType": "AC"
	}, {
		"party": {
			"displayValue": "***624",
			"value": "D0F62A5CEC53EB985DBA69D5373F9BECFA40137819A3"
		},
		"requestType": "UPDATE_AUTO_REPAYMENT",
		"requestData": "&#x7b;&quot;elements&quot;&#x3a;&#x5b;&#x7b;&quot;id&quot;&#x3a;&quot;SCH1&quot;,&quot;type&quot;&#x3a;&quot;SCH&quot;,&quot;label&quot;&#x3a;null,&quot;values&quot;&#x3a;&#x5b;&#x5d;&#x7d;,&#x7b;&quot;id&quot;&#x3a;&quot;FFTB3&quot;,&quot;type&quot;&#x3a;&quot;FFTB&quot;,&quot;label&quot;&#x3a;&quot;Enter 2 Wheeler Loan Amount &quot;,&quot;values&quot;&#x3a;&#x5b;&quot;9000&quot;&#x5d;&#x7d;,&#x7b;&quot;id&quot;&#x3a;&quot;FFMC5&quot;,&quot;type&quot;&#x3a;&quot;FFMC&quot;,&quot;label&quot;&#x3a;&quot;Req Type&quot;,&quot;values&quot;&#x3a;&#x5b;&quot;NI&quot;&#x5d;&#x7d;,&#x7b;&quot;id&quot;&#x3a;&quot;FFDL6&quot;,&quot;type&quot;&#x3a;&quot;FFDL&quot;,&quot;label&quot;&#x3a;&quot;Choose vehicle brand&quot;,&quot;values&quot;&#x3a;&#x5b;&quot;Honda&quot;&#x5d;&#x7d;,&#x7b;&quot;id&quot;&#x3a;&quot;SCH2&quot;,&quot;type&quot;&#x3a;&quot;SCH&quot;,&quot;label&quot;&#x3a;null,&quot;values&quot;&#x3a;&#x5b;&#x5d;&#x7d;,&#x7b;&quot;id&quot;&#x3a;&quot;FFTB4&quot;,&quot;type&quot;&#x3a;&quot;FFTB&quot;,&quot;label&quot;&#x3a;&quot;Enter 4 wheeler Loan Amount&quot;,&quot;values&quot;&#x3a;&#x5b;&quot;7666&quot;&#x5d;&#x7d;,&#x7b;&quot;id&quot;&#x3a;&quot;FFDL7&quot;,&quot;type&quot;&#x3a;&quot;FFDL&quot;,&quot;label&quot;&#x3a;&quot;Choose 4 V brand&quot;,&quot;values&quot;&#x3a;&#x5b;&quot;Honda&quot;&#x5d;&#x7d;&#x5d;&#x7d;",
		"entityTypeIdentifier": "66667777888894339",
		"status": "PE",
		"priority": "M",
		"creationDate": "2018-04-17T13:16:12.000Z",
		"id": "314",
		"entityTypeIdentifierKey": "DE",
		"lastUpdatedDate": "2018-04-17T13:16:12.157Z",
		"definitionId": "SR0000001345",
		"product": "Loan",
		"categoryType": "Loan Topup",
		"priorityType": "M",
		"entityType": "AC"
	}, {
		"party": {
			"displayValue": "***624",
			"value": "D0F62A5CEC53EB985DBA69D5373F9BECFA40137819A3"
		},
		"requestType": "UPDATE_AUTO_REPAYMENT",
		"requestData": "&#x7b;&quot;elements&quot;&#x3a;&#x5b;&#x7b;&quot;id&quot;&#x3a;&quot;SCH1&quot;,&quot;type&quot;&#x3a;&quot;SCH&quot;,&quot;label&quot;&#x3a;null,&quot;values&quot;&#x3a;&#x5b;&#x5d;&#x7d;,&#x7b;&quot;id&quot;&#x3a;&quot;FFTB3&quot;,&quot;type&quot;&#x3a;&quot;FFTB&quot;,&quot;label&quot;&#x3a;&quot;Enter 2 Wheeler Loan Amount &quot;,&quot;values&quot;&#x3a;&#x5b;&quot;1000&quot;&#x5d;&#x7d;,&#x7b;&quot;id&quot;&#x3a;&quot;FFMC5&quot;,&quot;type&quot;&#x3a;&quot;FFMC&quot;,&quot;label&quot;&#x3a;&quot;Req Type&quot;,&quot;values&quot;&#x3a;&#x5b;&quot;Immediate&quot;&#x5d;&#x7d;,&#x7b;&quot;id&quot;&#x3a;&quot;FFDL6&quot;,&quot;type&quot;&#x3a;&quot;FFDL&quot;,&quot;label&quot;&#x3a;&quot;Choose vehicle brand&quot;,&quot;values&quot;&#x3a;&#x5b;&quot;TVS&quot;&#x5d;&#x7d;,&#x7b;&quot;id&quot;&#x3a;&quot;SCH2&quot;,&quot;type&quot;&#x3a;&quot;SCH&quot;,&quot;label&quot;&#x3a;null,&quot;values&quot;&#x3a;&#x5b;&#x5d;&#x7d;,&#x7b;&quot;id&quot;&#x3a;&quot;FFTB4&quot;,&quot;type&quot;&#x3a;&quot;FFTB&quot;,&quot;label&quot;&#x3a;&quot;Enter 4 wheeler Loan Amount&quot;,&quot;values&quot;&#x3a;&#x5b;&quot;8999&quot;&#x5d;&#x7d;,&#x7b;&quot;id&quot;&#x3a;&quot;FFDL7&quot;,&quot;type&quot;&#x3a;&quot;FFDL&quot;,&quot;label&quot;&#x3a;&quot;Choose 4 V brand&quot;,&quot;values&quot;&#x3a;&#x5b;&quot;Maruti&quot;&#x5d;&#x7d;&#x5d;&#x7d;",
		"entityTypeIdentifier": "66667777888894339",
		"status": "PE",
		"priority": "M",
		"creationDate": "2018-04-17T13:14:15.000Z",
		"id": "313",
		"entityTypeIdentifierKey": "DE",
		"lastUpdatedDate": "2018-04-17T13:14:15.533Z",
		"definitionId": "SR0000001345",
		"product": "Loan",
		"categoryType": "Loan Topup",
		"priorityType": "M",
		"entityType": "AC"
	}, {
		"party": {
			"displayValue": "***624",
			"value": "D0F62A5CEC53EB985DBA69D5373F9BECFA40137819A3"
		},
		"requestType": "UPDATE_AUTO_REPAYMENT",
		"requestData": "&quot;&#x7b;&quot;elements&quot;&#x3a;&#x5b;&#x7b;&quot;id&quot;&#x3a;&quot;FFDL1&quot;,&quot;type&quot;&#x3a;&quot;FFDL&quot;,&quot;label&quot;&#x3a;&quot;Drop list&quot;,&quot;values&quot;&#x3a;&quot;value1&quot;&#x7d;&#x5d;&#x7d;&quot;",
		"entityTypeIdentifier": "66667777888894339",
		"status": "PE",
		"priority": "M",
		"creationDate": "2018-04-16T10:58:16.000Z",
		"id": "303",
		"entityTypeIdentifierKey": "DE",
		"lastUpdatedDate": "2018-04-16T10:58:16.331Z",
		"definitionId": "SR0000001266",
		"product": "Credit Card",
		"categoryType": "Credit Card Payment",
		"priorityType": "M",
		"entityType": "AC"
	}, {
		"party": {
			"displayValue": "***624",
			"value": "D0F62A5CEC53EB985DBA69D5373F9BECFA40137819A3"
		},
		"requestType": "UPDATE_AUTO_REPAYMENT",
		"requestData": "&quot;&#x7b;&quot;elements&quot;&#x3a;&#x5b;&#x7b;&quot;id&quot;&#x3a;&quot;PDSS3&quot;,&quot;type&quot;&#x3a;&quot;PDSS&quot;,&quot;label&quot;&#x3a;&quot;Salutation&quot;,&quot;values&quot;&#x3a;&quot;Other&quot;&#x7d;,&#x7b;&quot;id&quot;&#x3a;&quot;PDAN1&quot;,&quot;type&quot;&#x3a;&quot;PDAN&quot;,&quot;label&quot;&#x3a;&quot;Enter Account Number&quot;,&quot;values&quot;&#x3a;&quot;D3C433C1076C3F6A19B6666D4487BCA174DB8310A6E036679E263CD464&quot;&#x7d;,&#x7b;&quot;id&quot;&#x3a;&quot;PDGS2&quot;,&quot;type&quot;&#x3a;&quot;PDGS&quot;,&quot;label&quot;&#x3a;&quot;Enter Gender&quot;,&quot;values&quot;&#x3a;&quot;Male&quot;&#x7d;&#x5d;&#x7d;&quot;",
		"entityTypeIdentifier": "66667777888894339",
		"status": "PE",
		"priority": "M",
		"creationDate": "2018-04-16T10:50:41.000Z",
		"id": "302",
		"entityTypeIdentifierKey": "DE",
		"lastUpdatedDate": "2018-04-16T10:50:41.806Z",
		"definitionId": "SR0000001256",
		"product": "Account",
		"categoryType": "Closure related",
		"priorityType": "M",
		"entityType": "AC"
	}, {
		"party": {
			"displayValue": "***624",
			"value": "D0F62A5CEC53EB985DBA69D5373F9BECFA40137819A3"
		},
		"requestType": "UPDATE_AUTO_REPAYMENT",
		"requestData": "&quot;&#x7b;&quot;elements&quot;&#x3a;&#x5b;&#x7b;&quot;id&quot;&#x3a;&quot;PDSS3&quot;,&quot;type&quot;&#x3a;&quot;PDSS&quot;,&quot;label&quot;&#x3a;&quot;Salutation&quot;,&quot;values&quot;&#x3a;&quot;Mr&quot;&#x7d;,&#x7b;&quot;id&quot;&#x3a;&quot;PDAN1&quot;,&quot;type&quot;&#x3a;&quot;PDAN&quot;,&quot;label&quot;&#x3a;&quot;Enter Account Number&quot;,&quot;values&quot;&#x3a;&quot;D773283ACBDF5F07D64793A853F009E1D7368FF4EFE2326C42D5AEACCD&quot;&#x7d;,&#x7b;&quot;id&quot;&#x3a;&quot;PDGS2&quot;,&quot;type&quot;&#x3a;&quot;PDGS&quot;,&quot;label&quot;&#x3a;&quot;Enter Gender&quot;,&quot;values&quot;&#x3a;&quot;Male&quot;&#x7d;&#x5d;&#x7d;&quot;",
		"entityTypeIdentifier": "66667777888894339",
		"status": "PE",
		"priority": "M",
		"creationDate": "2018-04-16T10:36:40.000Z",
		"id": "301",
		"entityTypeIdentifierKey": "DE",
		"lastUpdatedDate": "2018-04-16T10:36:40.259Z",
		"definitionId": "SR0000001256",
		"product": "Account",
		"categoryType": "Closure related",
		"priorityType": "M",
		"entityType": "AC"
	}]
}
