{
    "productDetails": {
        "productName": "Credit Card",
        "productCode": "",
        "productStages": [{
            "id": "orientation",
            "previousStage": null,
            "nextStagename": "application-form",
            "name": "orientation",
            "sequenceNumber": 1,
            "isComplete": false,
            "location": "",
            "stages": null
        }, {
            "id": "application-form",
            "previousStage": "orientation",
            "nextStagename": "card-preferences",
            "name": "application",
            "sequenceNumber": 2,
            "isComplete": false,
            "location": "",
            "stages": [{
                "id": "personal-details",
                "previousStage": null,
                "nextStagename": "financial-template-base",
                "name": "personalDetails",
                "sequenceNumber": 1,
                "isComplete": false,
                "location": "",
                "stages": [{
                    "id": "primary-registration",
                    "previousStage": "expense-info",
                    "nextStagename": "identity-info",
                    "name": "primaryInformation",
                    "sequenceNumber": 1,
                    "isComplete": false,
                    "location": "",
                    "stages": null
                }, {
                    "id": "identity-info",
                    "previousStage": "primary-registration",
                    "nextStagename": "contact-info",
                    "name": "proofOfIdentity",
                    "sequenceNumber": 2,
                    "isComplete": false,
                    "location": "",
                    "stages": null
                }, {
                    "id": "contact-info",
                    "previousStage": "identity-info",
                    "nextStagename": "occupation-info",
                    "name": "contactInformation",
                    "sequenceNumber": 3,
                    "isComplete": false,
                    "location": "",
                    "stages": null
                }, {
                    "id": "occupation-info",
                    "previousStage": "contact-info",
                    "nextStagename": null,
                    "name": "employmentInformation",
                    "sequenceNumber": 4,
                    "isComplete": false,
                    "location": "",
                    "stages": null
                }]
            }, {
                "id": "financial-template-base",
                "previousStage": "occupation-info",
                "nextStagename": null,
                "name": "financialDetails",
                "sequenceNumber": 2,
                "isComplete": false,
                "location": "",
                "stages": [{
                    "id": "financial-details",
                    "previousStage": null,
                    "nextStagename": null,
                    "name": "financialDetails",
                    "sequenceNumber": 2,
                    "isComplete": false,
                    "location": "",
                    "stages": [{
                        "id": "income-info",
                        "previousStage": null,
                        "nextStagename": "expense-info",
                        "name": "income",
                        "sequenceNumber": 1,
                        "isComplete": false,
                        "location": "",
                        "stages": null,
                        "type": "INCOME"
                    }, {
                        "id": "expense-info",
                        "previousStage": "income-info",
                        "nextStagename": "assets-info",
                        "name": "expenses",
                        "sequenceNumber": 2,
                        "isComplete": false,
                        "location": "",
                        "stages": null,
                        "type": "EXPENSE"
                    }, {
                        "id": "assets-info",
                        "previousStage": "expense-info",
                        "nextStagename": "liabilities-info",
                        "name": "assets",
                        "sequenceNumber": 3,
                        "isComplete": false,
                        "location": "",
                        "stages": null,
                        "type": "ASSET"
                    }, {
                        "id": "liabilities-info",
                        "previousStage": "assets-info",
                        "nextStagename": "current-assets-info",
                        "name": "liabilities",
                        "sequenceNumber": 4,
                        "isComplete": false,
                        "location": "",
                        "stages": null,
                        "type": "LIABILITY"
                    }, {
                        "id": "current-assets-info",
                        "previousStage": "liabilities-info",
                        "nextStagename": "current-liabilities-info",
                        "name": "currentAssets",
                        "sequenceNumber": 5,
                        "isComplete": false,
                        "location": "",
                        "stages": null,
                        "type": "CURRENT-ASSET"
                    }, {
                        "id": "current-liabilities-info",
                        "previousStage": "current-assets-info",
                        "nextStagename": null,
                        "name": "currentLiabilities",
                        "sequenceNumber": 6,
                        "isComplete": false,
                        "location": "",
                        "stages": null,
                        "type": "CURRENT-LIABILITY"
                    }]
                }]
            }]
        }, {
            "id": "card-additional-details",
            "previousStage": "application-form",
            "nextStagename": "review",
            "name": "customizeYourCard",
            "sequenceNumber": 3,
            "isComplete": false,
            "location": "",
            "stages": [{
                "id": "customize-card",
                "previousStage": null,
                "nextStagename": null,
                "name": "customizeYourCard",
                "sequenceNumber": 1,
                "isComplete": false,
                "location": "",
                "stages": null
            }]
        }, {
            "id": "review",
            "previousStage": "card-additional-details",
            "nextStagename": "submission-confirmation",
            "name": "Review",
            "sequenceNumber": 4,
            "isComplete": false,
            "location": "",
            "stages": null
        }, {
            "id": "submission-confirmation",
            "previousStage": null,
            "nextStagename": null,
            "name": "submissionConfirmation",
            "sequenceNumber": 5,
            "isComplete": false,
            "location": "",
            "stages": null
        }]
    }
}
